uniquebible/htmlResources/images/exlbl/BL1.png
uniquebible/htmlResources/images/exlbl/BL10.png
uniquebible/htmlResources/images/exlbl/BL100.png
uniquebible/htmlResources/images/exlbl/BL1000.png
uniquebible/htmlResources/images/exlbl/BL1001.png
uniquebible/htmlResources/images/exlbl/BL1002.png
uniquebible/htmlResources/images/exlbl/BL1003.png
uniquebible/htmlResources/images/exlbl/BL1004.png
uniquebible/htmlResources/images/exlbl/BL1006.png
uniquebible/htmlResources/images/exlbl/BL1007.png
uniquebible/htmlResources/images/exlbl/BL1008.png
uniquebible/htmlResources/images/exlbl/BL1009.png
uniquebible/htmlResources/images/exlbl/BL101.png
uniquebible/htmlResources/images/exlbl/BL1012.png
uniquebible/htmlResources/images/exlbl/BL1013.png
uniquebible/htmlResources/images/exlbl/BL1014.png
uniquebible/htmlResources/images/exlbl/BL1016.png
uniquebible/htmlResources/images/exlbl/BL1017.png
uniquebible/htmlResources/images/exlbl/BL1018.png
uniquebible/htmlResources/images/exlbl/BL1019.png
uniquebible/htmlResources/images/exlbl/BL102.png
uniquebible/htmlResources/images/exlbl/BL1020.png
uniquebible/htmlResources/images/exlbl/BL1021.png
uniquebible/htmlResources/images/exlbl/BL1022.png
uniquebible/htmlResources/images/exlbl/BL1023.png
uniquebible/htmlResources/images/exlbl/BL1024.png
uniquebible/htmlResources/images/exlbl/BL1025.png
uniquebible/htmlResources/images/exlbl/BL1026.png
uniquebible/htmlResources/images/exlbl/BL1027.png
uniquebible/htmlResources/images/exlbl/BL1028.png
uniquebible/htmlResources/images/exlbl/BL1029.png
uniquebible/htmlResources/images/exlbl/BL103.png
uniquebible/htmlResources/images/exlbl/BL1030.png
uniquebible/htmlResources/images/exlbl/BL1032.png
uniquebible/htmlResources/images/exlbl/BL1034.png
uniquebible/htmlResources/images/exlbl/BL1037.png
uniquebible/htmlResources/images/exlbl/BL1038.png
uniquebible/htmlResources/images/exlbl/BL1039.png
uniquebible/htmlResources/images/exlbl/BL1040.png
uniquebible/htmlResources/images/exlbl/BL1041.png
uniquebible_maps_1-0.0.3.dist-info/LICENSE
uniquebible_maps_1-0.0.3.dist-info/METADATA
uniquebible_maps_1-0.0.3.dist-info/WHEEL
uniquebible_maps_1-0.0.3.dist-info/top_level.txt
uniquebible_maps_1-0.0.3.dist-info/RECORD
